{"expireTime":9007200819427210000,"key":"transformer-remark-markdown-ast-e1ddd650c6c89b79533a063e2701b494--","val":{"type":"root","children":[{"type":"paragraph","children":[{"type":"text","value":"This is my first blog post on my new (Accessible) Gatsby site!","position":{"start":{"line":2,"column":1,"offset":2},"end":{"line":2,"column":63,"offset":64},"indent":[]}}],"position":{"start":{"line":2,"column":1,"offset":2},"end":{"line":2,"column":63,"offset":64},"indent":[]}},{"type":"paragraph","children":[{"type":"text","value":"I love reading, hiking, running, and cats!","position":{"start":{"line":4,"column":1,"offset":68},"end":{"line":4,"column":43,"offset":110},"indent":[]}}],"position":{"start":{"line":4,"column":1,"offset":68},"end":{"line":4,"column":43,"offset":110},"indent":[]}},{"type":"paragraph","children":[{"type":"text","value":"Blah blah blah.","position":{"start":{"line":6,"column":1,"offset":114},"end":{"line":6,"column":16,"offset":129},"indent":[]}}],"position":{"start":{"line":6,"column":1,"offset":114},"end":{"line":6,"column":16,"offset":129},"indent":[]}}],"position":{"start":{"line":1,"column":1,"offset":0},"end":{"line":7,"column":1,"offset":131}}}}